md2pdf/__init__.py
md2pdf/version.json
md2pdf/bin/__init__.py
md2pdf/bin/main.py
md2pdf/core/__init__.py
md2pdf/core/converter.py
md2pdf/styles/default.css
md2pdf/styles/mermaid-config.json
md2pdf/utils/__init__.py
md2pdf/utils/checkbox.py
md2pdf/utils/formula.py
md2pdf/utils/mermaid.py
md2pdf_python-1.0.1.dist-info/METADATA
md2pdf_python-1.0.1.dist-info/WHEEL
md2pdf_python-1.0.1.dist-info/entry_points.txt
md2pdf_python-1.0.1.dist-info/top_level.txt
md2pdf_python-1.0.1.dist-info/RECORD
