Metadata-Version: 2.4
Name: md2pdf-python
Version: 1.0.1
Summary: A user-friendly tool for converting Markdown to PDF
Home-page: https://github.com/suqingdong/md2pdf
Author: suqingdong
Author-email: suqingdong1114@gmail.com
License: MIT License
Classifier: Development Status :: 5 - Production/Stable
Classifier: Operating System :: OS Independent
Classifier: Intended Audience :: Developers
Classifier: Programming Language :: Python
Classifier: Programming Language :: Python :: 3
Classifier: Programming Language :: Python :: 3.9
Classifier: Programming Language :: Python :: 3.10
Classifier: Programming Language :: Python :: 3.11
Classifier: Programming Language :: Python :: 3.12
Classifier: Topic :: Software Development :: Libraries
Requires-Dist: click
Requires-Dist: loguru
Requires-Dist: weasyprint
Requires-Dist: md2html-python
Dynamic: author
Dynamic: author-email
Dynamic: classifier
Dynamic: description
Dynamic: description-content-type
Dynamic: home-page
Dynamic: license
Dynamic: requires-dist
Dynamic: summary
